[{"Id":"da7fd10b-d046-4018-bc41-364f32fdb6c8","UserName":"elbek","Password":"123","Email":"elbek@latifov","Phone":"234567","UserPhoto":"/UserImages/6a267ec7-17d2-40fa-a609-758135d5e8ca.jpg","Attemps":[{"TicketIndex":0,"Attempts":0},{"TicketIndex":1,"Attempts":0},{"TicketIndex":2,"Attempts":0},{"TicketIndex":3,"Attempts":0},{"TicketIndex":4,"Attempts":0},{"TicketIndex":5,"Attempts":0},{"TicketIndex":6,"Attempts":0},{"TicketIndex":7,"Attempts":0},{"TicketIndex":8,"Attempts":0},{"TicketIndex":9,"Attempts":0},{"TicketIndex":10,"Attempts":0},{"TicketIndex":11,"Attempts":0},{"TicketIndex":12,"Attempts":0},{"TicketIndex":13,"Attempts":0},{"TicketIndex":14,"Attempts":0},{"TicketIndex":15,"Attempts":0},{"TicketIndex":16,"Attempts":0},{"TicketIndex":17,"Attempts":0},{"TicketIndex":18,"Attempts":0},{"TicketIndex":19,"Attempts":0},{"TicketIndex":20,"Attempts":0},{"TicketIndex":21,"Attempts":0},{"TicketIndex":22,"Attempts":0},{"TicketIndex":23,"Attempts":0},{"TicketIndex":24,"Attempts":0},{"TicketIndex":25,"Attempts":0},{"TicketIndex":26,"Attempts":0},{"TicketIndex":27,"Attempts":0},{"TicketIndex":28,"Attempts":0},{"TicketIndex":29,"Attempts":0},{"TicketIndex":30,"Attempts":0},{"TicketIndex":31,"Attempts":0},{"TicketIndex":32,"Attempts":0},{"TicketIndex":33,"Attempts":0},{"TicketIndex":34,"Attempts":0},{"TicketIndex":35,"Attempts":0},{"TicketIndex":36,"Attempts":0},{"TicketIndex":37,"Attempts":0},{"TicketIndex":38,"Attempts":0},{"TicketIndex":39,"Attempts":0},{"TicketIndex":40,"Attempts":0},{"TicketIndex":41,"Attempts":0},{"TicketIndex":42,"Attempts":0},{"TicketIndex":43,"Attempts":0},{"TicketIndex":44,"Attempts":0},{"TicketIndex":45,"Attempts":0},{"TicketIndex":46,"Attempts":0},{"TicketIndex":47,"Attempts":0},{"TicketIndex":48,"Attempts":0},{"TicketIndex":49,"Attempts":0},{"TicketIndex":50,"Attempts":0},{"TicketIndex":51,"Attempts":0},{"TicketIndex":52,"Attempts":0},{"TicketIndex":53,"Attempts":0},{"TicketIndex":54,"Attempts":0},{"TicketIndex":55,"Attempts":0},{"TicketIndex":56,"Attempts":0},{"TicketIndex":57,"Attempts":0},{"TicketIndex":58,"Attempts":0},{"TicketIndex":59,"Attempts":0},{"TicketIndex":60,"Attempts":0},{"TicketIndex":61,"Attempts":0},{"TicketIndex":62,"Attempts":0},{"TicketIndex":63,"Attempts":0},{"TicketIndex":64,"Attempts":0},{"TicketIndex":65,"Attempts":0},{"TicketIndex":66,"Attempts":0},{"TicketIndex":67,"Attempts":0},{"TicketIndex":68,"Attempts":0},{"TicketIndex":69,"Attempts":0}],"Results":[],"TicketInfo":[]}]